<manifest alg="2" build="2018.1.0.386" opt="true" iceEnabled="true" iceMarkupVersion="2" iceEnabledOptions="link,responsive,cachebuster,textStyling" exportTarget="other" domain="https://chachawash.github.io" resolutions="1x,2x" timestamp="1620241369471">
  <folder name="css">
    <file name="site_global.css" crc="444006867"/>
    <file name="index.css" crc="23608585" ref="index"/>
  </folder>
  <folder name="scripts">
    <file name="jquery-1.8.3.min.js" crc="209076791" ref="index"/>
    <file name="museutils.js" crc="340535759" ref="index"/>
    <file name="whatinput.js" crc="86476730" ref="index"/>
    <file name="museconfig.js" crc="310584261" ref="index"/>
    <file name="jquery.watch.js" crc="51536988" ref="index"/>
    <file name="require.js" crc="7928878" ref="index"/>
  </folder>
  <folder name="images">
    <file name="a-master-favicon.ico" crc="132953600" ref="index"/>
    <file name="company-logotype.png" crc="3770135762" seo="true" ref="index">
      <caption webpage="index" alt=""/>
    </file>
    <file name="company-logotype_2x.png" crc="4178673428" seo="true" ref="index">
      <caption webpage="index" alt=""/>
    </file>
    <file name="hero.jpg" crc="4251870522" seo="true" ref="index">
      <caption webpage="index" alt=""/>
    </file>
    <file name="hero_2x.jpg" crc="14147309" seo="true" ref="index">
      <caption webpage="index" alt=""/>
    </file>
    <file name="jp-a-2.png" crc="312304351" seo="true" ref="index">
      <caption webpage="index" alt=""/>
    </file>
    <file name="jp-a-2_2x.png" crc="3829698743" seo="true" ref="index">
      <caption webpage="index" alt=""/>
    </file>
    <file name="jp-a-1.png" crc="3892680096" seo="true" ref="index">
      <caption webpage="index" alt=""/>
    </file>
    <file name="jp-a-1_2x.png" crc="205697327" seo="true" ref="index">
      <caption webpage="index" alt=""/>
    </file>
    <file name="icon-01.png" crc="4124090786" seo="true" ref="index">
      <caption webpage="index" alt=""/>
    </file>
    <file name="icon-01_2x.png" crc="466621653" seo="true" ref="index">
      <caption webpage="index" alt=""/>
    </file>
    <file name="jp-b-1.png" crc="429020388" seo="true" ref="index">
      <caption webpage="index" alt=""/>
    </file>
    <file name="jp-b-1_2x.png" crc="3817178969" seo="true" ref="index">
      <caption webpage="index" alt=""/>
    </file>
    <file name="jp-b-2.png" crc="341931583" seo="true" ref="index">
      <caption webpage="index" alt=""/>
    </file>
    <file name="jp-b-2_2x.png" crc="210779403" seo="true" ref="index">
      <caption webpage="index" alt=""/>
    </file>
    <file name="pic-b-making.jpg" crc="4253931313" seo="true" ref="index">
      <caption webpage="index" alt=""/>
    </file>
    <file name="pic-b-making_2x.jpg" crc="4198883905" seo="true" ref="index">
      <caption webpage="index" alt=""/>
    </file>
    <file name="pic-b-seed.jpg" crc="434766247" seo="true" ref="index">
      <caption webpage="index" alt=""/>
    </file>
    <file name="pic-b-seed_2x.jpg" crc="330041445" seo="true" ref="index">
      <caption webpage="index" alt=""/>
    </file>
    <file name="jp-b-3.png" crc="3918410317" seo="true" ref="index">
      <caption webpage="index" alt=""/>
    </file>
    <file name="jp-b-3_2x.png" crc="3815554728" seo="true" ref="index">
      <caption webpage="index" alt=""/>
    </file>
    <file name="jp-b-4.png" crc="188203670" seo="true" ref="index">
      <caption webpage="index" alt=""/>
    </file>
    <file name="jp-b-4_2x.png" crc="4090078680" seo="true" ref="index">
      <caption webpage="index" alt=""/>
    </file>
    <file name="jp-b-5.png" crc="246569942" seo="true" ref="index">
      <caption webpage="index" alt=""/>
    </file>
    <file name="jp-b-5_2x.png" crc="112273752" seo="true" ref="index">
      <caption webpage="index" alt=""/>
    </file>
    <file name="jp-b-6.png" crc="227519592" seo="true" ref="index">
      <caption webpage="index" alt=""/>
    </file>
    <file name="jp-b-6_2x.png" crc="323452329" seo="true" ref="index">
      <caption webpage="index" alt=""/>
    </file>
    <file name="jp-b-7.png" crc="229107420" seo="true" ref="index">
      <caption webpage="index" alt=""/>
    </file>
    <file name="jp-b-7_2x.png" crc="4206275969" seo="true" ref="index">
      <caption webpage="index" alt=""/>
    </file>
    <file name="jp-b-8.png" crc="243271878" seo="true" ref="index">
      <caption webpage="index" alt=""/>
    </file>
    <file name="jp-b-8_2x.png" crc="229493545" seo="true" ref="index">
      <caption webpage="index" alt=""/>
    </file>
    <file name="icon-02.png" crc="185677042" seo="true" ref="index">
      <caption webpage="index" alt=""/>
    </file>
    <file name="icon-02_2x.png" crc="4216989914" seo="true" ref="index">
      <caption webpage="index" alt=""/>
    </file>
    <file name="jp-c-1.png" crc="360851289" seo="true" ref="index">
      <caption webpage="index" alt=""/>
    </file>
    <file name="jp-c-1_2x.png" crc="4162613635" seo="true" ref="index">
      <caption webpage="index" alt=""/>
    </file>
    <file name="jp-c-2.png" crc="3949989975" seo="true" ref="index">
      <caption webpage="index" alt=""/>
    </file>
    <file name="jp-c-2_2x.png" crc="4126650864" seo="true" ref="index">
      <caption webpage="index" alt=""/>
    </file>
    <file name="pic-c-powder-cube.jpg" crc="455151424" seo="true" ref="index">
      <caption webpage="index" alt=""/>
    </file>
    <file name="pic-c-powder-cube_2x.jpg" crc="261576628" seo="true" ref="index">
      <caption webpage="index" alt=""/>
    </file>
    <file name="jp-c-3.png" crc="2567683" seo="true" ref="index">
      <caption webpage="index" alt=""/>
    </file>
    <file name="jp-c-3_2x.png" crc="78259755" seo="true" ref="index">
      <caption webpage="index" alt=""/>
    </file>
    <file name="jp-c-4.png" crc="4288992070" seo="true" ref="index">
      <caption webpage="index" alt=""/>
    </file>
    <file name="jp-c-4_2x.png" crc="4230213510" seo="true" ref="index">
      <caption webpage="index" alt=""/>
    </file>
    <file name="jp-c-5.png" crc="3791675508" seo="true" ref="index">
      <caption webpage="index" alt=""/>
    </file>
    <file name="jp-c-5_2x.png" crc="4092740176" seo="true" ref="index">
      <caption webpage="index" alt=""/>
    </file>
    <file name="dishwasher.jpg" crc="178630145" seo="true" ref="index">
      <caption webpage="index" alt=""/>
    </file>
    <file name="dishwasher_2x.jpg" crc="193851571" seo="true" ref="index">
      <caption webpage="index" alt=""/>
    </file>
    <file name="icon-03.png" crc="4248659462" seo="true" ref="index">
      <caption webpage="index" alt=""/>
    </file>
    <file name="icon-03_2x.png" crc="3875286630" seo="true" ref="index">
      <caption webpage="index" alt=""/>
    </file>
    <file name="jp-d-1.png" crc="4205008087" seo="true" ref="index">
      <caption webpage="index" alt=""/>
    </file>
    <file name="jp-d-1_2x.png" crc="382729324" seo="true" ref="index">
      <caption webpage="index" alt=""/>
    </file>
    <file name="jp-d-5.png" crc="4809260" seo="true" ref="index">
      <caption webpage="index" alt=""/>
    </file>
    <file name="jp-d-5_2x.png" crc="3802578375" seo="true" ref="index">
      <caption webpage="index" alt=""/>
    </file>
    <file name="pic-d-oil-a.jpg" crc="4025118903" seo="true" ref="index">
      <caption webpage="index" alt=""/>
    </file>
    <file name="pic-d-oil-a_2x.jpg" crc="3824883523" seo="true" ref="index">
      <caption webpage="index" alt=""/>
    </file>
    <file name="jp-d-3.png" crc="3986983911" seo="true" ref="index">
      <caption webpage="index" alt=""/>
    </file>
    <file name="jp-d-3_2x.png" crc="3986983911" seo="true" ref="index">
      <caption webpage="index" alt=""/>
    </file>
    <file name="pic-d-before-after.jpg" crc="498237328" seo="true" ref="index">
      <caption webpage="index" alt=""/>
    </file>
    <file name="pic-d-before-after_2x.jpg" crc="5396495" seo="true" ref="index">
      <caption webpage="index" alt=""/>
    </file>
    <file name="jp-d-4.png" crc="3982725359" seo="true" ref="index">
      <caption webpage="index" alt=""/>
    </file>
    <file name="jp-d-4_2x.png" crc="3982725359" seo="true" ref="index">
      <caption webpage="index" alt=""/>
    </file>
    <file name="pic-d-oil-b.jpg" crc="506759161" seo="true" ref="index">
      <caption webpage="index" alt=""/>
    </file>
    <file name="pic-d-oil-b_2x.jpg" crc="283596891" seo="true" ref="index">
      <caption webpage="index" alt=""/>
    </file>
    <file name="jp-d-2.png" crc="184950022" seo="true" ref="index">
      <caption webpage="index" alt=""/>
    </file>
    <file name="jp-d-2_2x.png" crc="4020237139" seo="true" ref="index">
      <caption webpage="index" alt=""/>
    </file>
    <file name="icon-04.png" crc="24887184" seo="true" ref="index">
      <caption webpage="index" alt=""/>
    </file>
    <file name="icon-04_2x.png" crc="448913302" seo="true" ref="index">
      <caption webpage="index" alt=""/>
    </file>
    <file name="jp-e-1.png" crc="135477175" seo="true" ref="index">
      <caption webpage="index" alt=""/>
    </file>
    <file name="jp-e-1_2x.png" crc="361698874" seo="true" ref="index">
      <caption webpage="index" alt=""/>
    </file>
    <file name="jp-e-2.png" crc="4001310414" seo="true" ref="index">
      <caption webpage="index" alt=""/>
    </file>
    <file name="jp-e-2_2x.png" crc="426583315" seo="true" ref="index">
      <caption webpage="index" alt=""/>
    </file>
    <file name="pic-e-tea-saponin.png" crc="3982464981" seo="true" ref="index">
      <caption webpage="index" alt=""/>
    </file>
    <file name="pic-e-tea-saponin_2x.png" crc="3808510788" seo="true" ref="index">
      <caption webpage="index" alt=""/>
    </file>
    <file name="pic-e-ecoli.jpg" crc="4271122041" seo="true" ref="index">
      <caption webpage="index" alt=""/>
    </file>
    <file name="pic-e-ecoli_2x.jpg" crc="4181273010" seo="true" ref="index">
      <caption webpage="index" alt=""/>
    </file>
    <file name="jp-e-4.png" crc="345322887" seo="true" ref="index">
      <caption webpage="index" alt=""/>
    </file>
    <file name="jp-e-4_2x.png" crc="99126976" seo="true" ref="index">
      <caption webpage="index" alt=""/>
    </file>
    <file name="jp-e-3.png" crc="205588418" seo="true" ref="index">
      <caption webpage="index" alt=""/>
    </file>
    <file name="jp-e-3_2x.png" crc="3902214180" seo="true" ref="index">
      <caption webpage="index" alt=""/>
    </file>
    <file name="jp-e-5.png" crc="4194989740" seo="true" ref="index">
      <caption webpage="index" alt=""/>
    </file>
    <file name="jp-e-5_2x.png" crc="4055255750" seo="true" ref="index">
      <caption webpage="index" alt=""/>
    </file>
    <file name="jp-f-1.png" crc="3799911703" seo="true" ref="index">
      <caption webpage="index" alt=""/>
    </file>
    <file name="jp-f-1_2x.png" crc="3861207418" seo="true" ref="index">
      <caption webpage="index" alt=""/>
    </file>
    <file name="jp-f-2.png" crc="3785043550" seo="true" ref="index">
      <caption webpage="index" alt=""/>
    </file>
    <file name="jp-f-2_2x.png" crc="4098297748" seo="true" ref="index">
      <caption webpage="index" alt=""/>
    </file>
    <file name="jp-f-3.png" crc="3825296371" seo="true" ref="index">
      <caption webpage="index" alt=""/>
    </file>
    <file name="jp-f-3_2x.png" crc="3992188457" seo="true" ref="index">
      <caption webpage="index" alt=""/>
    </file>
    <file name="jp-f-4.png" crc="3797520884" seo="true" ref="index">
      <caption webpage="index" alt=""/>
    </file>
    <file name="jp-f-4_2x.png" crc="42148134" seo="true" ref="index">
      <caption webpage="index" alt=""/>
    </file>
    <file name="pic-f-cubes.jpg" crc="494449632" seo="true" ref="index">
      <caption webpage="index" alt=""/>
    </file>
    <file name="pic-f-cubes_2x.jpg" crc="456756399" seo="true" ref="index">
      <caption webpage="index" alt=""/>
    </file>
    <file name="icon-bottom-instagram.png" crc="205558892" seo="true" ref="index">
      <caption webpage="index" alt=""/>
    </file>
    <file name="icon-bottom-instagram_2x.png" crc="3888642622" seo="true" ref="index">
      <caption webpage="index" alt=""/>
    </file>
    <file name="icon-bottom-facebook.png" crc="3864595108" seo="true" ref="index">
      <caption webpage="index" alt=""/>
    </file>
    <file name="icon-bottom-facebook_2x.png" crc="3820568362" seo="true" ref="index">
      <caption webpage="index" alt=""/>
    </file>
    <file name="icon-bottom-messanger.png" crc="4095917894" seo="true" ref="index">
      <caption webpage="index" alt=""/>
    </file>
    <file name="icon-bottom-messanger_2x.png" crc="3858087318" seo="true" ref="index">
      <caption webpage="index" alt=""/>
    </file>
    <file name="icon-bottom-email.png" crc="464417899" seo="true" ref="index">
      <caption webpage="index" alt=""/>
    </file>
    <file name="icon-bottom-email_2x.png" crc="6706428" seo="true" ref="index">
      <caption webpage="index" alt=""/>
    </file>
  </folder>
  <file name="index.html" crc="265448459" seo="true" mt="1620241252589" redirect="true"/>
</manifest>